odoo10_addon_base_external_dbsource_odbc-10.0.1.0.0-py2.7-nspkg.pth
odoo10_addon_base_external_dbsource_odbc-10.0.1.0.0.dist-info/top_level.txt
odoo10_addon_base_external_dbsource_odbc-10.0.1.0.0.dist-info/WHEEL
odoo10_addon_base_external_dbsource_odbc-10.0.1.0.0.dist-info/RECORD
odoo10_addon_base_external_dbsource_odbc-10.0.1.0.0.dist-info/metadata.json
odoo10_addon_base_external_dbsource_odbc-10.0.1.0.0.dist-info/DESCRIPTION.rst
odoo10_addon_base_external_dbsource_odbc-10.0.1.0.0.dist-info/METADATA
odoo10_addon_base_external_dbsource_odbc-10.0.1.0.0.dist-info/namespace_packages.txt
odoo/addons/base_external_dbsource_odbc/__manifest__.py
odoo/addons/base_external_dbsource_odbc/__init__.py
odoo/addons/base_external_dbsource_odbc/README.rst
odoo/addons/base_external_dbsource_odbc/models/__init__.py
odoo/addons/base_external_dbsource_odbc/models/base_external_dbsource.py
odoo/addons/base_external_dbsource_odbc/tests/test_base_external_dbsource.py
odoo/addons/base_external_dbsource_odbc/tests/__init__.py
odoo/addons/base_external_dbsource_odbc/demo/base_external_dbsource.xml
